thymus/__init__.py
thymus/constants.py
thymus/freq_conversions.py
thymus/point.py
thymus/timeseries.py
thymus/tsproto.py
thymus/tssdict.py
thymus/tsslist.py
thymus/Thymus_timeseries.egg-info/PKG-INFO
thymus/Thymus_timeseries.egg-info/SOURCES.txt
thymus/Thymus_timeseries.egg-info/dependency_links.txt
thymus/Thymus_timeseries.egg-info/requires.txt
thymus/Thymus_timeseries.egg-info/top_level.txt
thymus/__pycache__/__init__.cpython-311.pyc
thymus/__pycache__/constants.cpython-311.pyc
thymus/__pycache__/freq_conversions.cpython-311.pyc
thymus/__pycache__/point.cpython-311.pyc
thymus/__pycache__/timeseries.cpython-311.pyc
thymus/__pycache__/tsproto.cpython-311.pyc
thymus/__pycache__/tssdict.cpython-311.pyc
thymus/__pycache__/tsslist.cpython-311.pyc
Thymus_timeseries-0.3.5.dist-info/METADATA
Thymus_timeseries-0.3.5.dist-info/WHEEL
Thymus_timeseries-0.3.5.dist-info/top_level.txt
Thymus_timeseries-0.3.5.dist-info/RECORD
