Metadata-Version: 2.1
Name: Thymus-timeseries
Version: 0.3.5
Summary: An intuitive library tracking dates and timeseries in common using NumPy arrays.
Author-email: Don Smiley <dsmiley@sidorof.com>
License: MIT License
Project-URL: Homepage, https://github.com/sidorof/Thymus-timeseries
Project-URL: Doc_URL, https://sidorof.github.io/Thymus-timeseries/
Requires-Python: >=3.10
Requires-Dist: numpy
